Metadata-Version: 1.1
Name: shipnames
Version: 0.0.1
Summary:  Get random ship names from Ian Banks' Culture novels
Home-page: https://github.com/signalrock/shipnames
Author: signal
Author-email: raulcearock@gmail.com
License: BSD
Download-URL: https://github.com/signalrock/shipnames/tarball/0.0.1
Platform: UNKNOWN
Classifier: Development Status :: 3 - Alpha
Classifier: Intended Audience :: Developers
Classifier: Programming Language :: Python :: 3
